gdicons/__init__.py
gdicons/plist.py
gdicons/script.py
gdicons/templates/colors.json
gdicons-1.2.0.dist-info/LICENSE
gdicons-1.2.0.dist-info/METADATA
gdicons-1.2.0.dist-info/WHEEL
gdicons-1.2.0.dist-info/top_level.txt
gdicons-1.2.0.dist-info/RECORD
