Metadata-Version: 2.1
Name: gdicons
Version: 1.2.0
Summary: Render Geometry Dash icons
Author-email: Bradley Pierce <bituvocoding@gmail.com>
License: GNU AFFERO GENERAL PUBLIC LICENSE
Keywords: geometry,dash,icon,render
Classifier: License :: OSI Approved :: GNU General Public License v3 (GPLv3)
Classifier: Operating System :: Microsoft :: Windows
Classifier: Topic :: Software Development :: Libraries :: Python Modules
Classifier: Topic :: Multimedia :: Graphics
Classifier: Topic :: Games/Entertainment
Classifier: Programming Language :: Python
Classifier: Programming Language :: Python :: 3
Classifier: Programming Language :: Python :: 3.12
Requires-Python: >=3.9
License-File: LICENSE
Requires-Dist: pillow >=10.3.0
